stripecaller/__init__.py
stripecaller/callers.py
stripecaller-0.1.1.data/scripts/call-stripes
stripecaller-0.1.1.data/scripts/pileup-stripes
stripecaller-0.1.1.data/scripts/stripe-plot
stripecaller-0.1.1.dist-info/LICENSE
stripecaller-0.1.1.dist-info/METADATA
stripecaller-0.1.1.dist-info/WHEEL
stripecaller-0.1.1.dist-info/top_level.txt
stripecaller-0.1.1.dist-info/RECORD
