Metadata-Version: 2.1
Name: stripecaller
Version: 0.1.1
Summary: Automated Stripe Identification from contact matrix.
Home-page: https://github.com/XiaoTaoWang/StripeCaller/
Author: XiaoTao Wang
Author-email: wangxiaotao686@gmail.com
Keywords: chromatin contact-matrix 3D genome stripe cooler
Classifier: Programming Language :: Python :: 3 :: Only
Classifier: License :: OSI Approved :: GNU General Public License v3 or later (GPLv3+)
Classifier: Operating System :: POSIX
Classifier: Development Status :: 4 - Beta
Classifier: Intended Audience :: Science/Research
Classifier: Topic :: Scientific/Engineering :: Bio-Informatics
License-File: LICENSE
